konfi/__init__.py
konfi/converter.py
konfi/converters.py
konfi/field.py
konfi/loader.py
konfi/source.py
konfi/templ.py
konfi/typeinspect.py
konfi/sources/__init__.py
konfi/sources/env.py
konfi/sources/file.py
konfi/sources/toml.py
konfi/sources/yaml.py
konfi-0.2.1.dist-info/LICENSE
konfi-0.2.1.dist-info/METADATA
konfi-0.2.1.dist-info/WHEEL
konfi-0.2.1.dist-info/top_level.txt
konfi-0.2.1.dist-info/RECORD
