Metadata-Version: 2.1
Name: konfi
Version: 0.2.1
Summary: Python config management, but cute.
Home-page: https://github.com/gieseladev/konfi
Author: Giesela Inc.
Author-email: team@giesela.dev
License: MIT
Platform: UNKNOWN
Requires-Dist: toml
Requires-Dist: pyyaml
Provides-Extra: docs
Requires-Dist: sphinx ; extra == 'docs'
Requires-Dist: sphinx-autodoc-typehints ; extra == 'docs'
